{
  "namespaces": [
    "public"
  ],
  "name": "public",
  "tables": [
    {
      "columns": {
        "id": {
          "name": "id",
          "type": "uuid",
          "unsigned": false,
          "autoincrement": false,
          "primary": false,
          "nullable": false,
          "default": "uuid_generate_v4()",
          "mappedType": "uuid"
        },
        "status": {
          "name": "status",
          "type": "text",
          "unsigned": false,
          "autoincrement": false,
          "primary": false,
          "nullable": false,
          "default": "'pending'",
          "enumItems": [
            "pending",
            "progress",
            "done"
          ],
          "mappedType": "enum"
        },
        "planned_date": {
          "name": "planned_date",
          "type": "timestamptz(0)",
          "unsigned": false,
          "autoincrement": false,
          "primary": false,
          "nullable": false,
          "length": 6,
          "mappedType": "datetime"
        },
        "created_at": {
          "name": "created_at",
          "type": "timestamptz(0)",
          "unsigned": false,
          "autoincrement": false,
          "primary": false,
          "nullable": false,
          "length": 6,
          "mappedType": "datetime"
        }
      },
      "name": "match",
      "schema": "public",
      "indexes": [
        {
          "keyName": "match_pkey",
          "columnNames": [
            "id"
          ],
          "composite": false,
          "primary": true,
          "unique": true
        }
      ],
      "checks": [],
      "foreignKeys": {}
    },
    {
      "columns": {
        "id": {
          "name": "id",
          "type": "uuid",
          "unsigned": false,
          "autoincrement": false,
          "primary": false,
          "nullable": false,
          "default": "uuid_generate_v4()",
          "mappedType": "uuid"
        },
        "rank": {
          "name": "rank",
          "type": "int",
          "unsigned": false,
          "autoincrement": false,
          "primary": false,
          "nullable": false,
          "default": "1000",
          "mappedType": "integer"
        },
        "rating": {
          "name": "rating",
          "type": "int",
          "unsigned": false,
          "autoincrement": false,
          "primary": false,
          "nullable": false,
          "default": "1000",
          "mappedType": "integer"
        },
        "victory": {
          "name": "victory",
          "type": "int",
          "unsigned": false,
          "autoincrement": false,
          "primary": false,
          "nullable": false,
          "default": "0",
          "mappedType": "integer"
        },
        "defeat": {
          "name": "defeat",
          "type": "int",
          "unsigned": false,
          "autoincrement": false,
          "primary": false,
          "nullable": false,
          "default": "0",
          "mappedType": "integer"
        }
      },
      "name": "player",
      "schema": "public",
      "indexes": [
        {
          "keyName": "player_pkey",
          "columnNames": [
            "id"
          ],
          "composite": false,
          "primary": true,
          "unique": true
        }
      ],
      "checks": [],
      "foreignKeys": {}
    },
    {
      "columns": {
        "id": {
          "name": "id",
          "type": "uuid",
          "unsigned": false,
          "autoincrement": false,
          "primary": false,
          "nullable": false,
          "default": "uuid_generate_v4()",
          "mappedType": "uuid"
        },
        "player_id": {
          "name": "player_id",
          "type": "uuid",
          "unsigned": false,
          "autoincrement": false,
          "primary": false,
          "nullable": false,
          "mappedType": "uuid"
        },
        "match_id": {
          "name": "match_id",
          "type": "uuid",
          "unsigned": false,
          "autoincrement": false,
          "primary": false,
          "nullable": false,
          "mappedType": "uuid"
        },
        "league": {
          "name": "league",
          "type": "text",
          "unsigned": false,
          "autoincrement": false,
          "primary": false,
          "nullable": false,
          "default": "'bronze'",
          "enumItems": [
            "bronze",
            "silver",
            "gold"
          ],
          "mappedType": "enum"
        }
      },
      "name": "player_to_match",
      "schema": "public",
      "indexes": [
        {
          "keyName": "player_to_match_pkey",
          "columnNames": [
            "id",
            "player_id",
            "match_id"
          ],
          "composite": true,
          "primary": true,
          "unique": true
        }
      ],
      "checks": [],
      "foreignKeys": {
        "player_to_match_player_id_foreign": {
          "constraintName": "player_to_match_player_id_foreign",
          "columnNames": [
            "player_id"
          ],
          "localTableName": "public.player_to_match",
          "referencedColumnNames": [
            "id"
          ],
          "referencedTableName": "public.player",
          "updateRule": "cascade"
        },
        "player_to_match_match_id_foreign": {
          "constraintName": "player_to_match_match_id_foreign",
          "columnNames": [
            "match_id"
          ],
          "localTableName": "public.player_to_match",
          "referencedColumnNames": [
            "id"
          ],
          "referencedTableName": "public.match",
          "updateRule": "cascade"
        }
      }
    },
    {
      "columns": {
        "id": {
          "name": "id",
          "type": "uuid",
          "unsigned": false,
          "autoincrement": false,
          "primary": false,
          "nullable": false,
          "default": "uuid_generate_v4()",
          "mappedType": "uuid"
        },
        "username": {
          "name": "username",
          "type": "varchar(255)",
          "unsigned": false,
          "autoincrement": false,
          "primary": false,
          "nullable": false,
          "mappedType": "string"
        },
        "email": {
          "name": "email",
          "type": "varchar(255)",
          "unsigned": false,
          "autoincrement": false,
          "primary": false,
          "nullable": false,
          "mappedType": "string"
        },
        "hashed_password": {
          "name": "hashed_password",
          "type": "varchar(255)",
          "unsigned": false,
          "autoincrement": false,
          "primary": false,
          "nullable": false,
          "mappedType": "string"
        },
        "roles": {
          "name": "roles",
          "type": "text[]",
          "unsigned": false,
          "autoincrement": false,
          "primary": false,
          "nullable": false,
          "default": "'{visitor}'",
          "enumItems": [
            "visitor",
            "admin",
            "superadmin"
          ],
          "mappedType": "array"
        },
        "player_id": {
          "name": "player_id",
          "type": "uuid",
          "unsigned": false,
          "autoincrement": false,
          "primary": false,
          "nullable": false,
          "mappedType": "uuid"
        }
      },
      "name": "user",
      "schema": "public",
      "indexes": [
        {
          "columnNames": [
            "username"
          ],
          "composite": false,
          "keyName": "user_username_unique",
          "primary": false,
          "unique": true
        },
        {
          "columnNames": [
            "email"
          ],
          "composite": false,
          "keyName": "user_email_unique",
          "primary": false,
          "unique": true
        },
        {
          "columnNames": [
            "player_id"
          ],
          "composite": false,
          "keyName": "user_player_id_unique",
          "primary": false,
          "unique": true
        },
        {
          "keyName": "user_username_email_unique",
          "columnNames": [
            "username",
            "email"
          ],
          "composite": true,
          "primary": false,
          "unique": true
        },
        {
          "keyName": "user_pkey",
          "columnNames": [
            "id"
          ],
          "composite": false,
          "primary": true,
          "unique": true
        }
      ],
      "checks": [],
      "foreignKeys": {
        "user_player_id_foreign": {
          "constraintName": "user_player_id_foreign",
          "columnNames": [
            "player_id"
          ],
          "localTableName": "public.user",
          "referencedColumnNames": [
            "id"
          ],
          "referencedTableName": "public.player",
          "updateRule": "cascade"
        }
      }
    },
    {
      "columns": {
        "id": {
          "name": "id",
          "type": "uuid",
          "unsigned": false,
          "autoincrement": false,
          "primary": false,
          "nullable": false,
          "default": "uuid_generate_v4()",
          "mappedType": "uuid"
        },
        "is_player": {
          "name": "is_player",
          "type": "boolean",
          "unsigned": false,
          "autoincrement": false,
          "primary": false,
          "nullable": false,
          "default": "true",
          "mappedType": "boolean"
        },
        "battletag": {
          "name": "battletag",
          "type": "varchar(255)",
          "unsigned": false,
          "autoincrement": false,
          "primary": false,
          "nullable": false,
          "default": "''",
          "mappedType": "string"
        },
        "user_id": {
          "name": "user_id",
          "type": "uuid",
          "unsigned": false,
          "autoincrement": false,
          "primary": false,
          "nullable": false,
          "mappedType": "uuid"
        },
        "player_id": {
          "name": "player_id",
          "type": "uuid",
          "unsigned": false,
          "autoincrement": false,
          "primary": false,
          "nullable": false,
          "mappedType": "uuid"
        }
      },
      "name": "profile",
      "schema": "public",
      "indexes": [
        {
          "columnNames": [
            "user_id"
          ],
          "composite": false,
          "keyName": "profile_user_id_unique",
          "primary": false,
          "unique": true
        },
        {
          "columnNames": [
            "player_id"
          ],
          "composite": false,
          "keyName": "profile_player_id_unique",
          "primary": false,
          "unique": true
        },
        {
          "keyName": "profile_pkey",
          "columnNames": [
            "id"
          ],
          "composite": false,
          "primary": true,
          "unique": true
        }
      ],
      "checks": [],
      "foreignKeys": {
        "profile_user_id_foreign": {
          "constraintName": "profile_user_id_foreign",
          "columnNames": [
            "user_id"
          ],
          "localTableName": "public.profile",
          "referencedColumnNames": [
            "id"
          ],
          "referencedTableName": "public.user",
          "updateRule": "cascade"
        },
        "profile_player_id_foreign": {
          "constraintName": "profile_player_id_foreign",
          "columnNames": [
            "player_id"
          ],
          "localTableName": "public.profile",
          "referencedColumnNames": [
            "id"
          ],
          "referencedTableName": "public.player",
          "updateRule": "cascade"
        }
      }
    },
    {
      "columns": {
        "id": {
          "name": "id",
          "type": "uuid",
          "unsigned": false,
          "autoincrement": false,
          "primary": false,
          "nullable": false,
          "default": "uuid_generate_v4()",
          "mappedType": "uuid"
        },
        "title": {
          "name": "title",
          "type": "varchar(255)",
          "unsigned": false,
          "autoincrement": false,
          "primary": false,
          "nullable": false,
          "mappedType": "string"
        },
        "content": {
          "name": "content",
          "type": "varchar(255)",
          "unsigned": false,
          "autoincrement": false,
          "primary": false,
          "nullable": false,
          "mappedType": "string"
        },
        "user_id": {
          "name": "user_id",
          "type": "uuid",
          "unsigned": false,
          "autoincrement": false,
          "primary": false,
          "nullable": false,
          "mappedType": "uuid"
        }
      },
      "name": "article",
      "schema": "public",
      "indexes": [
        {
          "keyName": "article_pkey",
          "columnNames": [
            "id"
          ],
          "composite": false,
          "primary": true,
          "unique": true
        }
      ],
      "checks": [],
      "foreignKeys": {
        "article_user_id_foreign": {
          "constraintName": "article_user_id_foreign",
          "columnNames": [
            "user_id"
          ],
          "localTableName": "public.article",
          "referencedColumnNames": [
            "id"
          ],
          "referencedTableName": "public.user",
          "updateRule": "cascade"
        }
      }
    }
  ]
}
